pwlreg/__about__.py
pwlreg/__init__.py
pwlreg/pwlreg.py
pwlreg-1.0.3.dist-info/METADATA
pwlreg-1.0.3.dist-info/WHEEL
pwlreg-1.0.3.dist-info/RECORD
