Metadata-Version: 2.4
Name: pwlreg
Version: 1.0.3
Summary: A scikit-learn-compatible implementation of Piecewise Linear Regression
Project-URL: Documentation, https://ensley-nexant.github.io/pwlreg
Project-URL: Source, https://github.com/ensley-nexant/pwlreg
Project-URL: Issues, https://github.com/ensley-nexant/pwlreg/issues
Project-URL: Changelog, https://github.com/ensley-nexant/pwlreg/releases
Author-email: John Ensley <jensley@resource-innovations.com>
License-Expression: Apache-2.0
Keywords: change point,piecewise regression,scikit-learn,sklearn
Requires-Dist: numpy>=1.24.1
Requires-Dist: scikit-learn>=1.2.0
Requires-Dist: scipy>=1.9.3
